itpminer/__init__.py
itpminer/itp_miner.py
itpminer/utils/__init__.py
itpminer/utils/association_rules.py
itpminer/utils/rules_graph.py
itpminer/utils/types.py
itpminer/utils/components/DatList.py
itpminer/utils/components/ErrorChecker.py
itpminer/utils/components/ExtendedItem.py
itpminer/utils/components/Node.py
itpminer/utils/components/Pattern.py
itpminer/utils/components/__init__.py
itpminer-0.0.12.dist-info/LICENSE
itpminer-0.0.12.dist-info/METADATA
itpminer-0.0.12.dist-info/WHEEL
itpminer-0.0.12.dist-info/dependency_links.txt
itpminer-0.0.12.dist-info/top_level.txt
itpminer-0.0.12.dist-info/RECORD
