Metadata-Version: 2.1
Name: itpminer
Version: 0.0.12
Summary: Python implementation of ITPMiner algorithm
Home-page: https://github.com/Local-E-Rewards-ML/itpminer
Author: Local E
Author-email: csong@locale.app
License: MIT license
Keywords: itpminer
Platform: UNKNOWN
Classifier: Development Status :: 2 - Pre-Alpha
Classifier: Intended Audience :: Developers
Classifier: License :: OSI Approved :: MIT License
Classifier: Natural Language :: English
Classifier: Programming Language :: Python :: 3
Classifier: Programming Language :: Python :: 3.5
Classifier: Programming Language :: Python :: 3.6
Classifier: Programming Language :: Python :: 3.7
Classifier: Programming Language :: Python :: 3.8
Requires-Python: >=3.5
License-File: LICENSE
Requires-Dist: pandas
Requires-Dist: matplotlib-base
Requires-Dist: networkx
